kustomize/__init__.py
kustomize/generators.py
kustomize/main.py
kustomize-0.6.0.dist-info/LICENSE
kustomize-0.6.0.dist-info/METADATA
kustomize-0.6.0.dist-info/WHEEL
kustomize-0.6.0.dist-info/entry_points.txt
kustomize-0.6.0.dist-info/top_level.txt
kustomize-0.6.0.dist-info/RECORD
