Metadata-Version: 2.1
Name: kustomize
Version: 0.6.0
Summary: Kustomize for Kubernetes, but in Python
Author-email: Diogo Baeder <diogobaeder@yahoo.com.br>
Project-URL: Homepage, https://github.com/coherent-oss/python-kustomize
Classifier: Development Status :: 5 - Production/Stable
Classifier: Intended Audience :: Developers
Classifier: License :: OSI Approved :: MIT License
Classifier: Programming Language :: Python :: 3
Classifier: Programming Language :: Python :: 3 :: Only
Requires-Python: >=3.8
License-File: LICENSE
Provides-Extra: docs
Requires-Dist: sphinx >=3.5 ; extra == 'docs'
Requires-Dist: jaraco.packaging >=9.3 ; extra == 'docs'
Requires-Dist: rst.linker >=1.9 ; extra == 'docs'
Requires-Dist: furo ; extra == 'docs'
Requires-Dist: sphinx-lint ; extra == 'docs'
Requires-Dist: PyYAML ; extra == 'docs'
Provides-Extra: testing
Requires-Dist: pytest !=8.1.*,>=6 ; extra == 'testing'
Requires-Dist: pytest-checkdocs >=2.4 ; extra == 'testing'
Requires-Dist: pytest-cov ; extra == 'testing'
Requires-Dist: pytest-mypy ; extra == 'testing'
Requires-Dist: pytest-enabler >=2.2 ; extra == 'testing'
Requires-Dist: pytest-ruff >=0.2.1 ; extra == 'testing'
Requires-Dist: coverage ; extra == 'testing'
Requires-Dist: PyYAML ; extra == 'testing'
Requires-Dist: types-PyYAML ; extra == 'testing'
Requires-Dist: attrs ; extra == 'testing'
Requires-Dist: Pydantic >=2.0 ; extra == 'testing'
